matrix_utils/__init__.py
matrix_utils/aggregation.py
matrix_utils/array_mapper.py
matrix_utils/errors.py
matrix_utils/indexers.py
matrix_utils/mapped_matrix.py
matrix_utils/mapped_matrix_dict.py
matrix_utils/resource_group.py
matrix_utils/utils.py
matrix_utils-0.6.dist-info/LICENSE
matrix_utils-0.6.dist-info/METADATA
matrix_utils-0.6.dist-info/WHEEL
matrix_utils-0.6.dist-info/top_level.txt
matrix_utils-0.6.dist-info/RECORD
